{"materials":[{"id":"956","path":"Resources/unity_builtin_extra\\Default-Material","assetBundleId":"-2","data":["Default-Material",0,"64",2000,0,[["_Cutoff",0.5],["_Glossiness",0.5],["_GlossMapScale",1],["_SmoothnessTextureChannel",0],["_Metallic",0],["_SpecularHighlights",1],["_GlossyReflections",1],["_BumpScale",1],["_Parallax",0.0199999995529652],["_OcclusionStrength",1],["_DetailNormalMapScale",1],["_UVSec",0],["_Mode",0],["_SrcBlend",1],["_DstBlend",0],["_ZWrite",1]],[["_Color",1,1,1,1],["_EmissionColor",0,0,0,0.999999940395355]],[["_MainTex_ST",1,1,0,0],["_MetallicGlossMap_ST",1,1,0,0],["_BumpMap_ST",1,1,0,0],["_ParallaxMap_ST",1,1,0,0],["_OcclusionMap_ST",1,1,0,0],["_EmissionMap_ST",1,1,0,0],["_DetailMask_ST",1,1,0,0],["_DetailAlbedoMap_ST",1,1,0,0],["_DetailNormalMap_ST",1,1,0,0]],[["_MainTex",null,null],["_MetallicGlossMap",null,null],["_BumpMap",null,null],["_ParallaxMap",null,null],["_OcclusionMap",null,null],["_EmissionMap",null,null],["_DetailMask",null,null],["_DetailAlbedoMap",null,null],["_DetailNormalMap",null,null]],[]]},{"id":"958","path":"Resources/unity_builtin_extra\\Default-Skybox","assetBundleId":"-2","data":["Default-Skybox",0,"150",1000,0,[["_SunDisk",1],["_SunSize",0.0399999991059303],["_SunSizeConvergence",5],["_AtmosphereThickness",1],["_Exposure",1.29999995231628]],[["_SkyTint",0.5,0.5,0.5,1],["_GroundColor",0.368999987840652,0.349000006914139,0.340999990701675,1]],[],[],[["_SUNDISK_SIMPLE",1]]]}],"shaders":[{"id":"288","assetBundleId":"-2","data":[[],"Mobile/Particles/Additive","0000000000000000f000000000000000",["FOG_LINEAR","FOG_EXP","FOG_EXP2"],[[0,0,"",0,0,[4,null],[0,null],[0,null],[[5,null],[1,null],[0,null]],[[5,null],[1,null],[0,null]],[15,null],[0,null],[0,null],[0,null],[255,null],[255,null],[[0,null],[0,null],[0,null],[8,null]],[[0,null],[0,null],[0,null],[8,null]],[[0,null],[0,null],[0,null],[8,null]],[["QUEUE","Transparent"],["IGNOREPROJECTOR","true"],["RENDERTYPE","Transparent"],["PREVIEWTYPE","Plane"]],["FOG_LINEAR","FOG_EXP","FOG_EXP2"],[[0,0,[],0,1,0]],[],0]],[],[["_MainTex",4,0,0,0,0,"white"]],null,null,0,0]},{"id":"116","assetBundleId":"-2","data":[[],"Legacy Shaders/Transparent/Cutout/Diffuse","0000000000000000f000000000000000",["DIRECTIONAL","SHADOWS_SCREEN","LIGHTMAP_ON","DIRLIGHTMAP_COMBINED","LIGHTPROBE_SH","FOG_LINEAR","FOG_EXP","FOG_EXP2","VERTEXLIGHT_ON","SPOT","DIRECTIONAL_COOKIE","POINT","POINT_COOKIE"],[[0,0,"FORWARD",4,0,[4,null],[1,null],[2,null],[[1,null],[0,null],[0,null]],[[1,null],[0,null],[0,null]],[14,null],[0,null],[0,null],[0,null],[255,null],[255,null],[[0,null],[0,null],[0,null],[8,null]],[[0,null],[0,null],[0,null],[8,null]],[[0,null],[0,null],[0,null],[8,null]],[["LIGHTMODE","FORWARDBASE"],["QUEUE","AlphaTest"],["IGNOREPROJECTOR","true"],["SHADOWSUPPORT","true"],["RENDERTYPE","TransparentCutout"]],["DIRECTIONAL","SHADOWS_SCREEN","LIGHTMAP_ON","DIRLIGHTMAP_COMBINED","DYNAMICLIGHTMAP_ON","LIGHTMAP_SHADOW_MIXING","SHADOWS_SHADOWMASK","LIGHTPROBE_SH","FOG_LINEAR","FOG_EXP","FOG_EXP2","VERTEXLIGHT_ON","INSTANCING_ON"],[[0,0,["DIRECTIONAL"],2,3,0],[0,0,["DIRECTIONAL","SHADOWS_SCREEN"],4,5,0],[0,0,["DIRECTIONAL","VERTEXLIGHT_ON"],2,3,0],[0,0,["DIRECTIONAL","LIGHTPROBE_SH","SHADOWS_SCREEN"],6,7,0],[0,0,["DIRECTIONAL","LIGHTPROBE_SH","VERTEXLIGHT_ON"],8,9,0],[0,0,["DIRECTIONAL","SHADOWS_SCREEN","VERTEXLIGHT_ON"],4,5,0],[0,0,["DIRECTIONAL","LIGHTPROBE_SH","SHADOWS_SCREEN","VERTEXLIGHT_ON"],10,7,0]],[[0,0,["DIRECTIONAL","LIGHTPROBE_SH"],null,null,0]],0],[1,0,"FORWARD",5,0,[4,null],[0,null],[2,null],[[1,null],[1,null],[0,null]],[[1,null],[1,null],[0,null]],[14,null],[0,null],[0,null],[0,null],[255,null],[255,null],[[0,null],[0,null],[0,null],[8,null]],[[0,null],[0,null],[0,null],[8,null]],[[0,null],[0,null],[0,null],[8,null]],[["LIGHTMODE","FORWARDADD"],["QUEUE","AlphaTest"],["IGNOREPROJECTOR","true"],["RENDERTYPE","TransparentCutout"]],["SPOT","DIRECTIONAL","DIRECTIONAL_COOKIE","POINT","POINT_COOKIE","FOG_LINEAR","FOG_EXP","FOG_EXP2"],[[1,0,["POINT"],11,12,0],[1,0,["DIRECTIONAL"],13,3,0],[1,0,["SPOT"],14,15,0],[1,0,["POINT_COOKIE"],11,16,0],[1,0,["DIRECTIONAL_COOKIE"],17,18,0]],[],0]],[],[["_Color",0,1,1,1,1,""],["_MainTex",4,0,0,0,0,"white"],["_Cutoff",3,0.5,0,1,0,""]],0,"114",0,0]},{"id":"20","assetBundleId":"-2","data":[[],"Legacy Shaders/Diffuse","0000000000000000f000000000000000",["DIRECTIONAL","SHADOWS_SCREEN","LIGHTMAP_ON","DIRLIGHTMAP_COMBINED","LIGHTPROBE_SH","FOG_LINEAR","FOG_EXP","FOG_EXP2","VERTEXLIGHT_ON","SPOT","DIRECTIONAL_COOKIE","POINT","POINT_COOKIE"],[[0,0,"FORWARD",4,0,[4,null],[1,null],[2,null],[[1,null],[0,null],[0,null]],[[1,null],[0,null],[0,null]],[15,null],[0,null],[0,null],[0,null],[255,null],[255,null],[[0,null],[0,null],[0,null],[8,null]],[[0,null],[0,null],[0,null],[8,null]],[[0,null],[0,null],[0,null],[8,null]],[["LIGHTMODE","FORWARDBASE"],["SHADOWSUPPORT","true"],["RENDERTYPE","Opaque"]],["DIRECTIONAL","SHADOWS_SCREEN","LIGHTMAP_ON","DIRLIGHTMAP_COMBINED","DYNAMICLIGHTMAP_ON","LIGHTMAP_SHADOW_MIXING","SHADOWS_SHADOWMASK","LIGHTPROBE_SH","FOG_LINEAR","FOG_EXP","FOG_EXP2","VERTEXLIGHT_ON","INSTANCING_ON"],[[0,0,["DIRECTIONAL"],2,19,0],[0,0,["DIRECTIONAL","LIGHTPROBE_SH"],20,21,0],[0,0,["DIRECTIONAL","SHADOWS_SCREEN"],4,22,0],[0,0,["DIRECTIONAL","VERTEXLIGHT_ON"],2,19,0],[0,0,["DIRECTIONAL","LIGHTPROBE_SH","SHADOWS_SCREEN"],6,23,0],[0,0,["DIRECTIONAL","LIGHTPROBE_SH","VERTEXLIGHT_ON"],8,21,0],[0,0,["DIRECTIONAL","SHADOWS_SCREEN","VERTEXLIGHT_ON"],4,22,0],[0,0,["DIRECTIONAL","LIGHTPROBE_SH","SHADOWS_SCREEN","VERTEXLIGHT_ON"],10,23,0]],[],0],[1,0,"FORWARD",5,0,[4,null],[0,null],[2,null],[[1,null],[1,null],[0,null]],[[1,null],[1,null],[0,null]],[15,null],[0,null],[0,null],[0,null],[255,null],[255,null],[[0,null],[0,null],[0,null],[8,null]],[[0,null],[0,null],[0,null],[8,null]],[[0,null],[0,null],[0,null],[8,null]],[["LIGHTMODE","FORWARDADD"],["RENDERTYPE","Opaque"]],["SPOT","DIRECTIONAL","DIRECTIONAL_COOKIE","POINT","POINT_COOKIE","FOG_LINEAR","FOG_EXP","FOG_EXP2"],[[1,0,["POINT"],11,24,0],[1,0,["DIRECTIONAL"],13,19,0],[1,0,["SPOT"],14,25,0],[1,0,["POINT_COOKIE"],11,26,0],[1,0,["DIRECTIONAL_COOKIE"],17,27,0]],[],0]],[],[["_Color",0,1,1,1,1,""],["_MainTex",4,0,0,0,0,"white"]],0,"68",0,0]},{"id":"386","assetBundleId":"-2","data":[[],"Hidden/TextCore/Distance Field","0000000000000000f000000000000000",[],[[0,0,"",0,0,[8,null],[0,null],[0,null],[[1,null],[10,null],[0,null]],[[1,null],[10,null],[0,null]],[15,null],[0,null],[0,null],[0,null],[255,null],[255,null],[[0,null],[0,null],[0,null],[8,null]],[[0,null],[0,null],[0,null],[8,null]],[[0,null],[0,null],[0,null],[8,null]],[["FORCESUPPORTED","true"]],[],[[0,0,[],28,29,0]],[[0,0,[],null,null,0]],0]],[],[["_FaceColor",0,1,1,1,1,""],["_FaceDilate",3,0,-1,1,0,""],["_OutlineColor",0,0,0,0,1,""],["_OutlineWidth",3,0,0,1,0,""],["_OutlineSoftness",3,0,0,1,0,""],["_WeightNormal",2,0,0,0,0,""],["_WeightBold",2,0.5,0,0,0,""],["_ScaleRatioA",2,1,0,0,0,""],["_ScaleRatioB",2,1,0,0,0,""],["_ScaleRatioC",2,1,0,0,0,""],["_MainTex",4,0,0,0,0,"white"],["_GradientScale",2,10,0,0,0,""],["_ScaleX",2,1,0,0,0,""],["_ScaleY",2,1,0,0,0,""],["_Sharpness",3,0,-1,1,0,""],["_VertexOffsetX",2,0,0,0,0,""],["_VertexOffsetY",2,0,0,0,0,""]],null,null,0,0]},{"id":"30","assetBundleId":"-2","data":[[],"UI/Default","0000000000000000f000000000000000",["UNITY_UI_CLIP_RECT","UNITY_UI_ALPHACLIP"],[[0,0,"Default",0,0,[0,"unity_GUIZTestMode"],[0,null],[0,null],[[1,null],[10,null],[0,null]],[[1,null],[10,null],[0,null]],[0,"_ColorMask"],[0,null],[0,null],[0,"_Stencil"],[0,"_StencilReadMask"],[0,"_StencilWriteMask"],[[0,"_StencilOp"],[0,null],[0,null],[0,"_StencilComp"]],[[0,null],[0,null],[0,null],[8,null]],[[0,null],[0,null],[0,null],[8,null]],[["QUEUE","Transparent"],["IGNOREPROJECTOR","true"],["RENDERTYPE","Transparent"],["CANUSESPRITEATLAS","true"],["PREVIEWTYPE","Plane"]],["UNITY_UI_CLIP_RECT","UNITY_UI_ALPHACLIP"],[[0,0,[],30,31,0],[0,0,["UNITY_UI_ALPHACLIP"],30,32,0],[0,0,["UNITY_UI_CLIP_RECT"],30,33,0],[0,0,["UNITY_UI_ALPHACLIP","UNITY_UI_CLIP_RECT"],30,34,0]],[],0]],[],[["_MainTex",4,0,0,0,0,"white"],["_Color",0,1,1,1,1,""],["_StencilComp",2,8,0,0,0,""],["_Stencil",2,0,0,0,0,""],["_StencilOp",2,0,0,0,0,""],["_StencilWriteMask",2,255,0,0,0,""],["_StencilReadMask",2,255,0,0,0,""],["_ColorMask",2,15,0,0,0,""],["_UseUIAlphaClip",2,0,0,0,0,""]],null,null,0,0]},{"id":"114","assetBundleId":"-2","data":[[],"Legacy Shaders/Transparent/Cutout/VertexLit","0000000000000000f000000000000000",["SPOT","POINT","FOG_LINEAR","FOG_EXP","FOG_EXP2","SHADOWS_DEPTH"],[[0,0,"",1,0,[4,null],[1,null],[2,null],[[1,null],[0,null],[0,null]],[[1,null],[0,null],[0,null]],[14,null],[0,null],[0,null],[0,null],[255,null],[255,null],[[0,null],[0,null],[0,null],[8,null]],[[0,null],[0,null],[0,null],[8,null]],[[0,null],[0,null],[0,null],[8,null]],[["LIGHTMODE","Vertex"],["QUEUE","AlphaTest"],["IGNOREPROJECTOR","true"],["RENDERTYPE","TransparentCutout"]],["SPOT","POINT","FOG_LINEAR","FOG_EXP","FOG_EXP2"],[[0,0,[],35,36,0],[0,0,["POINT"],37,36,0],[0,0,["SPOT"],38,36,0]],[],0],[1,0,"",2,0,[4,null],[1,null],[2,null],[[1,null],[0,null],[0,null]],[[1,null],[0,null],[0,null]],[14,null],[0,null],[0,null],[0,null],[255,null],[255,null],[[0,null],[0,null],[0,null],[8,null]],[[0,null],[0,null],[0,null],[8,null]],[[0,null],[0,null],[0,null],[8,null]],[["LIGHTMODE","VertexLM"],["QUEUE","AlphaTest"],["IGNOREPROJECTOR","true"],["RENDERTYPE","TransparentCutout"]],["FOG_LINEAR","FOG_EXP","FOG_EXP2"],[[1,0,[],39,40,0]],[],0],[2,0,"Caster",8,0,[4,null],[1,null],[2,null],[[1,null],[0,null],[0,null]],[[1,null],[0,null],[0,null]],[15,null],[0,null],[0,null],[0,null],[255,null],[255,null],[[0,null],[0,null],[0,null],[8,null]],[[0,null],[0,null],[0,null],[8,null]],[[0,null],[0,null],[0,null],[8,null]],[["LIGHTMODE","SHADOWCASTER"],["QUEUE","AlphaTest"],["IGNOREPROJECTOR","true"],["SHADOWSUPPORT","true"],["RENDERTYPE","TransparentCutout"]],["SHADOWS_DEPTH","SHADOWS_CUBE","INSTANCING_ON"],[[2,0,["SHADOWS_DEPTH"],41,42,0]],[],0]],[],[["_Color",0,1,1,1,1,""],["_SpecColor",0,1,1,1,0,""],["_Emission",0,0,0,0,0,""],["_Shininess",3,0.699999988079071,0.100000001490116,1,0,""],["_MainTex",4,0,0,0,0,"white"],["_Cutoff",3,0.5,0,1,0,""]],null,null,0,0]},{"id":"150","assetBundleId":"-2","data":[[],"Skybox/Procedural","0000000000000000f000000000000000",["_SUNDISK_NONE","_SUNDISK_SIMPLE","_SUNDISK_HIGH_QUALITY"],[[0,0,"",0,0,[4,null],[0,null],[0,null],[[1,null],[0,null],[0,null]],[[1,null],[0,null],[0,null]],[15,null],[0,null],[0,null],[0,null],[255,null],[255,null],[[0,null],[0,null],[0,null],[8,null]],[[0,null],[0,null],[0,null],[8,null]],[[0,null],[0,null],[0,null],[8,null]],[["QUEUE","Background"],["RENDERTYPE","Background"],["PREVIEWTYPE","Skybox"]],["_SUNDISK_NONE","_SUNDISK_SIMPLE","_SUNDISK_HIGH_QUALITY"],[[0,0,["_SUNDISK_NONE"],43,44,0],[0,0,["_SUNDISK_SIMPLE"],45,46,0],[0,0,["_SUNDISK_HIGH_QUALITY"],47,48,0]],[],0]],[],[["_SunDisk",2,2,0,0,0,""],["_SunSize",3,0.0399999991059303,0,1,0,""],["_SunSizeConvergence",3,5,1,10,0,""],["_AtmosphereThickness",3,1,0,5,0,""],["_SkyTint",0,0.5,0.5,0.5,1,""],["_GroundColor",0,0.368999987840652,0.349000006914139,0.340999990701675,1,""],["_Exposure",3,1.29999995231628,0,8,0,""]],null,null,0,0]},{"id":"290","assetBundleId":"-2","data":[[],"Mobile/Particles/Alpha Blended","0000000000000000f000000000000000",["FOG_LINEAR","FOG_EXP","FOG_EXP2"],[[0,0,"",0,0,[4,null],[0,null],[0,null],[[5,null],[10,null],[0,null]],[[5,null],[10,null],[0,null]],[15,null],[0,null],[0,null],[0,null],[255,null],[255,null],[[0,null],[0,null],[0,null],[8,null]],[[0,null],[0,null],[0,null],[8,null]],[[0,null],[0,null],[0,null],[8,null]],[["QUEUE","Transparent"],["IGNOREPROJECTOR","true"],["RENDERTYPE","Transparent"],["PREVIEWTYPE","Plane"]],["FOG_LINEAR","FOG_EXP","FOG_EXP2"],[[0,0,[],49,1,0]],[],0]],[],[["_MainTex",4,0,0,0,0,"white"]],null,null,0,0]},{"id":"296","assetBundleId":"-2","data":[[],"Unlit/Transparent","0000000000000000f000000000000000",["FOG_LINEAR","FOG_EXP","FOG_EXP2"],[[0,0,"",0,0,[4,null],[0,null],[2,null],[[5,null],[10,null],[0,null]],[[5,null],[10,null],[0,null]],[15,null],[0,null],[0,null],[0,null],[255,null],[255,null],[[0,null],[0,null],[0,null],[8,null]],[[0,null],[0,null],[0,null],[8,null]],[[0,null],[0,null],[0,null],[8,null]],[["QUEUE","Transparent"],["IGNOREPROJECTOR","true"],["RENDERTYPE","Transparent"]],["FOG_LINEAR","FOG_EXP","FOG_EXP2"],[[0,0,[],50,51,0]],[],0]],[],[["_MainTex",4,0,0,0,0,"white"]],null,null,0,0]},{"id":"68","assetBundleId":"-2","data":[[],"Legacy Shaders/VertexLit","0000000000000000f000000000000000",["SPOT","POINT","FOG_LINEAR","FOG_EXP","FOG_EXP2","SHADOWS_DEPTH"],[[0,0,"",1,0,[4,null],[1,null],[2,null],[[1,null],[0,null],[0,null]],[[1,null],[0,null],[0,null]],[15,null],[0,null],[0,null],[0,null],[255,null],[255,null],[[0,null],[0,null],[0,null],[8,null]],[[0,null],[0,null],[0,null],[8,null]],[[0,null],[0,null],[0,null],[8,null]],[["LIGHTMODE","Vertex"],["RENDERTYPE","Opaque"]],["SPOT","POINT","FOG_LINEAR","FOG_EXP","FOG_EXP2"],[[0,0,[],35,61,0],[0,0,["POINT"],37,61,0],[0,0,["SPOT"],38,61,0]],[],0],[1,0,"",2,0,[4,null],[1,null],[2,null],[[1,null],[0,null],[0,null]],[[1,null],[0,null],[0,null]],[15,null],[0,null],[0,null],[0,null],[255,null],[255,null],[[0,null],[0,null],[0,null],[8,null]],[[0,null],[0,null],[0,null],[8,null]],[[0,null],[0,null],[0,null],[8,null]],[["LIGHTMODE","VertexLM"],["RENDERTYPE","Opaque"]],["FOG_LINEAR","FOG_EXP","FOG_EXP2"],[[1,0,[],62,63,0]],[],0],[2,0,"ShadowCaster",8,0,[4,null],[1,null],[2,null],[[1,null],[0,null],[0,null]],[[1,null],[0,null],[0,null]],[15,null],[0,null],[0,null],[0,null],[255,null],[255,null],[[0,null],[0,null],[0,null],[8,null]],[[0,null],[0,null],[0,null],[8,null]],[[0,null],[0,null],[0,null],[8,null]],[["LIGHTMODE","SHADOWCASTER"],["SHADOWSUPPORT","true"],["RENDERTYPE","Opaque"]],["SHADOWS_DEPTH","SHADOWS_CUBE","INSTANCING_ON"],[[2,0,["SHADOWS_DEPTH"],64,65,0]],[],0]],[],[["_Color",0,1,1,1,1,""],["_SpecColor",0,1,1,1,1,""],["_Emission",0,0,0,0,0,""],["_Shininess",3,0.699999988079071,0.00999999977648258,1,0,""],["_MainTex",4,0,0,0,0,"white"]],null,null,0,0]},{"id":"8","assetBundleId":"-2","data":[[],"Hidden/Internal-ScreenSpaceShadows","0000000000000000f000000000000000",["SHADOWS_SPLIT_SPHERES","SHADOWS_SINGLE_CASCADE"],[[0,0,"",0,0,[8,null],[0,null],[0,null],[[1,null],[0,null],[0,null]],[[1,null],[0,null],[0,null]],[15,null],[0,null],[0,null],[0,null],[255,null],[255,null],[[0,null],[0,null],[0,null],[8,null]],[[0,null],[0,null],[0,null],[8,null]],[[0,null],[0,null],[0,null],[8,null]],[["SHADOWMAPFILTER","HardShadow"]],["SHADOWS_SPLIT_SPHERES","SHADOWS_SINGLE_CASCADE"],[[0,0,[],66,67,1],[0,0,["SHADOWS_SPLIT_SPHERES"],66,68,1],[0,0,["SHADOWS_SINGLE_CASCADE"],66,69,1],[0,0,["SHADOWS_SINGLE_CASCADE","SHADOWS_SPLIT_SPHERES"],66,69,1]],[],1],[0,2,"",0,0,[8,null],[0,null],[0,null],[[1,null],[0,null],[0,null]],[[1,null],[0,null],[0,null]],[15,null],[0,null],[0,null],[0,null],[255,null],[255,null],[[0,null],[0,null],[0,null],[8,null]],[[0,null],[0,null],[0,null],[8,null]],[[0,null],[0,null],[0,null],[8,null]],[["SHADOWMAPFILTER","PCF_SOFT"]],["SHADOWS_SPLIT_SPHERES","SHADOWS_SINGLE_CASCADE"],[[0,2,[],66,70,1],[0,2,["SHADOWS_SPLIT_SPHERES"],66,71,1],[0,2,["SHADOWS_SINGLE_CASCADE"],66,72,1],[0,2,["SHADOWS_SINGLE_CASCADE","SHADOWS_SPLIT_SPHERES"],66,72,1]],[],1],[0,0,"",0,0,[8,null],[0,null],[0,null],[[1,null],[0,null],[0,null]],[[1,null],[0,null],[0,null]],[15,null],[0,null],[0,null],[0,null],[255,null],[255,null],[[0,null],[0,null],[0,null],[8,null]],[[0,null],[0,null],[0,null],[8,null]],[[0,null],[0,null],[0,null],[8,null]],[["SHADOWMAPFILTER","HardShadow"]],["SHADOWS_SPLIT_SPHERES","SHADOWS_SINGLE_CASCADE"],[[0,0,[],66,67,1],[0,0,["SHADOWS_SPLIT_SPHERES"],66,68,1],[0,0,["SHADOWS_SINGLE_CASCADE"],66,69,1],[0,0,["SHADOWS_SINGLE_CASCADE","SHADOWS_SPLIT_SPHERES"],66,69,1]],[],1]],[],[["_ShadowMapTexture",4,0,0,0,0,""],["_ODSWorldTexture",4,0,0,0,0,""]],null,null,1,0]},{"id":"64","assetBundleId":"-2","data":[[],"Standard","0000000000000000f000000000000000",["DIRECTIONAL","SHADOWS_SCREEN","LIGHTMAP_ON","DIRLIGHTMAP_COMBINED","LIGHTPROBE_SH","FOG_LINEAR","FOG_EXP","FOG_EXP2","_EMISSION","VERTEXLIGHT_ON","_NORMALMAP","_ALPHATEST_ON","_ALPHABLEND_ON","_ALPHAPREMULTIPLY_ON","_METALLICGLOSSMAP","_PARALLAXMAP","_DETAIL_MULX2","_SMOOTHNESS_TEXTURE_ALBEDO_CHANNEL_A","_SPECULARHIGHLIGHTS_OFF","_GLOSSYREFLECTIONS_OFF","SPOT","DIRECTIONAL_COOKIE","POINT","POINT_COOKIE","SHADOWS_DEPTH"],[[0,0,"FORWARD",4,0,[4,null],[0,"_ZWrite"],[2,null],[[0,"_SrcBlend"],[0,"_DstBlend"],[0,null]],[[0,"_SrcBlend"],[0,"_DstBlend"],[0,null]],[15,null],[0,null],[0,null],[0,null],[255,null],[255,null],[[0,null],[0,null],[0,null],[8,null]],[[0,null],[0,null],[0,null],[8,null]],[[0,null],[0,null],[0,null],[8,null]],[["LIGHTMODE","FORWARDBASE"],["SHADOWSUPPORT","true"],["RENDERTYPE","Opaque"],["PERFORMANCECHECKS","False"]],["DIRECTIONAL","SHADOWS_SCREEN","LIGHTMAP_ON","DIRLIGHTMAP_COMBINED","DYNAMICLIGHTMAP_ON","LIGHTMAP_SHADOW_MIXING","SHADOWS_SHADOWMASK","LIGHTPROBE_SH","FOG_LINEAR","FOG_EXP","FOG_EXP2","_EMISSION","VERTEXLIGHT_ON","INSTANCING_ON","_NORMALMAP","_ALPHATEST_ON","_ALPHABLEND_ON","_ALPHAPREMULTIPLY_ON","_METALLICGLOSSMAP","_PARALLAXMAP","_DETAIL_MULX2","_SMOOTHNESS_TEXTURE_ALBEDO_CHANNEL_A","_SPECULARHIGHLIGHTS_OFF","_GLOSSYREFLECTIONS_OFF"],[[0,0,["DIRECTIONAL"],73,74,0],[0,0,["DIRECTIONAL","LIGHTPROBE_SH"],75,76,0],[0,0,["DIRECTIONAL","SHADOWS_SCREEN"],77,78,0],[0,0,["DIRECTIONAL","VERTEXLIGHT_ON"],73,74,0],[0,0,["DIRECTIONAL","_ALPHATEST_ON"],73,79,0],[0,0,["DIRECTIONAL","_ALPHABLEND_ON"],73,80,0],[0,0,["DIRECTIONAL","_ALPHAPREMULTIPLY_ON"],73,81,0],[0,0,["DIRECTIONAL","_EMISSION"],73,82,0],[0,0,["DIRECTIONAL","_SMOOTHNESS_TEXTURE_ALBEDO_CHANNEL_A"],73,83,0],[0,0,["DIRECTIONAL","LIGHTPROBE_SH","_ALPHATEST_ON"],75,84,0],[0,0,["DIRECTIONAL","LIGHTPROBE_SH","_ALPHABLEND_ON"],75,85,0],[0,0,["DIRECTIONAL","LIGHTPROBE_SH","_ALPHAPREMULTIPLY_ON"],75,86,0],[0,0,["DIRECTIONAL","SHADOWS_SCREEN","_ALPHATEST_ON"],77,87,0],[0,0,["DIRECTIONAL","SHADOWS_SCREEN","_ALPHABLEND_ON"],77,88,0],[0,0,["DIRECTIONAL","SHADOWS_SCREEN","_ALPHAPREMULTIPLY_ON"],77,89,0],[0,0,["DIRECTIONAL","LIGHTPROBE_SH","SHADOWS_SCREEN"],90,91,0],[0,0,["DIRECTIONAL","VERTEXLIGHT_ON","_ALPHATEST_ON"],73,79,0],[0,0,["DIRECTIONAL","VERTEXLIGHT_ON","_ALPHABLEND_ON"],73,80,0],[0,0,["DIRECTIONAL","VERTEXLIGHT_ON","_ALPHAPREMULTIPLY_ON"],73,81,0],[0,0,["DIRECTIONAL","LIGHTPROBE_SH","VERTEXLIGHT_ON"],92,76,0],[0,0,["DIRECTIONAL","SHADOWS_SCREEN","VERTEXLIGHT_ON"],77,78,0],[0,0,["DIRECTIONAL","LIGHTPROBE_SH","_EMISSION"],75,93,0],[0,0,["DIRECTIONAL","LIGHTPROBE_SH","_SMOOTHNESS_TEXTURE_ALBEDO_CHANNEL_A"],75,94,0],[0,0,["DIRECTIONAL","SHADOWS_SCREEN","_EMISSION"],77,95,0],[0,0,["DIRECTIONAL","SHADOWS_SCREEN","_SMOOTHNESS_TEXTURE_ALBEDO_CHANNEL_A"],77,96,0],[0,0,["DIRECTIONAL","VERTEXLIGHT_ON","_EMISSION"],73,82,0],[0,0,["DIRECTIONAL","VERTEXLIGHT_ON","_SMOOTHNESS_TEXTURE_ALBEDO_CHANNEL_A"],73,83,0],[0,0,["DIRECTIONAL","_EMISSION","_ALPHAPREMULTIPLY_ON"],73,97,0],[0,0,["DIRECTIONAL","LIGHTPROBE_SH","SHADOWS_SCREEN","_ALPHATEST_ON"],90,98,0],[0,0,["DIRECTIONAL","LIGHTPROBE_SH","SHADOWS_SCREEN","_ALPHABLEND_ON"],90,99,0],[0,0,["DIRECTIONAL","LIGHTPROBE_SH","SHADOWS_SCREEN","_ALPHAPREMULTIPLY_ON"],90,100,0],[0,0,["DIRECTIONAL","LIGHTPROBE_SH","VERTEXLIGHT_ON","_ALPHATEST_ON"],92,84,0],[0,0,["DIRECTIONAL","LIGHTPROBE_SH","VERTEXLIGHT_ON","_ALPHABLEND_ON"],92,85,0],[0,0,["DIRECTIONAL","LIGHTPROBE_SH","VERTEXLIGHT_ON","_ALPHAPREMULTIPLY_ON"],92,86,0],[0,0,["DIRECTIONAL","SHADOWS_SCREEN","VERTEXLIGHT_ON","_ALPHATEST_ON"],77,87,0],[0,0,["DIRECTIONAL","SHADOWS_SCREEN","VERTEXLIGHT_ON","_ALPHABLEND_ON"],77,88,0],[0,0,["DIRECTIONAL","SHADOWS_SCREEN","VERTEXLIGHT_ON","_ALPHAPREMULTIPLY_ON"],77,89,0],[0,0,["DIRECTIONAL","LIGHTPROBE_SH","SHADOWS_SCREEN","VERTEXLIGHT_ON"],101,91,0],[0,0,["DIRECTIONAL","LIGHTPROBE_SH","_EMISSION","_ALPHAPREMULTIPLY_ON"],75,102,0],[0,0,["DIRECTIONAL","SHADOWS_SCREEN","_EMISSION","_ALPHAPREMULTIPLY_ON"],77,103,0],[0,0,["DIRECTIONAL","LIGHTPROBE_SH","SHADOWS_SCREEN","_EMISSION"],90,104,0],[0,0,["DIRECTIONAL","LIGHTPROBE_SH","SHADOWS_SCREEN","_SMOOTHNESS_TEXTURE_ALBEDO_CHANNEL_A"],90,105,0],[0,0,["DIRECTIONAL","VERTEXLIGHT_ON","_EMISSION","_ALPHAPREMULTIPLY_ON"],73,97,0],[0,0,["DIRECTIONAL","LIGHTPROBE_SH","VERTEXLIGHT_ON","_EMISSION"],92,93,0],[0,0,["DIRECTIONAL","LIGHTPROBE_SH","VERTEXLIGHT_ON","_SMOOTHNESS_TEXTURE_ALBEDO_CHANNEL_A"],92,94,0],[0,0,["DIRECTIONAL","SHADOWS_SCREEN","VERTEXLIGHT_ON","_EMISSION"],77,95,0],[0,0,["DIRECTIONAL","SHADOWS_SCREEN","VERTEXLIGHT_ON","_SMOOTHNESS_TEXTURE_ALBEDO_CHANNEL_A"],77,96,0],[0,0,["DIRECTIONAL","LIGHTPROBE_SH","SHADOWS_SCREEN","VERTEXLIGHT_ON","_ALPHATEST_ON"],101,98,0],[0,0,["DIRECTIONAL","LIGHTPROBE_SH","SHADOWS_SCREEN","VERTEXLIGHT_ON","_ALPHABLEND_ON"],101,99,0],[0,0,["DIRECTIONAL","LIGHTPROBE_SH","SHADOWS_SCREEN","VERTEXLIGHT_ON","_ALPHAPREMULTIPLY_ON"],101,100,0],[0,0,["DIRECTIONAL","LIGHTPROBE_SH","SHADOWS_SCREEN","_EMISSION","_ALPHAPREMULTIPLY_ON"],90,106,0],[0,0,["DIRECTIONAL","LIGHTPROBE_SH","VERTEXLIGHT_ON","_EMISSION","_ALPHAPREMULTIPLY_ON"],92,102,0],[0,0,["DIRECTIONAL","SHADOWS_SCREEN","VERTEXLIGHT_ON","_EMISSION","_ALPHAPREMULTIPLY_ON"],77,103,0],[0,0,["DIRECTIONAL","LIGHTPROBE_SH","SHADOWS_SCREEN","VERTEXLIGHT_ON","_EMISSION"],101,104,0],[0,0,["DIRECTIONAL","LIGHTPROBE_SH","SHADOWS_SCREEN","VERTEXLIGHT_ON","_SMOOTHNESS_TEXTURE_ALBEDO_CHANNEL_A"],101,105,0],[0,0,["DIRECTIONAL","LIGHTPROBE_SH","SHADOWS_SCREEN","VERTEXLIGHT_ON","_EMISSION","_ALPHAPREMULTIPLY_ON"],101,106,0]],[],0],[1,0,"FORWARD_DELTA",5,0,[4,null],[0,null],[2,null],[[0,"_SrcBlend"],[1,null],[0,null]],[[0,"_SrcBlend"],[1,null],[0,null]],[15,null],[0,null],[0,null],[0,null],[255,null],[255,null],[[0,null],[0,null],[0,null],[8,null]],[[0,null],[0,null],[0,null],[8,null]],[[0,null],[0,null],[0,null],[8,null]],[["LIGHTMODE","FORWARDADD"],["SHADOWSUPPORT","true"],["RENDERTYPE","Opaque"],["PERFORMANCECHECKS","False"]],["SPOT","DIRECTIONAL","DIRECTIONAL_COOKIE","POINT","POINT_COOKIE","SHADOWS_DEPTH","SHADOWS_SCREEN","SHADOWS_CUBE","SHADOWS_SOFT","LIGHTMAP_SHADOW_MIXING","SHADOWS_SHADOWMASK","FOG_LINEAR","FOG_EXP","FOG_EXP2","_NORMALMAP","_ALPHATEST_ON","_ALPHABLEND_ON","_ALPHAPREMULTIPLY_ON","_METALLICGLOSSMAP","_PARALLAXMAP","_SMOOTHNESS_TEXTURE_ALBEDO_CHANNEL_A","_SPECULARHIGHLIGHTS_OFF","_DETAIL_MULX2"],[[1,0,["POINT"],107,108,0],[1,0,["DIRECTIONAL"],109,110,0],[1,0,["SPOT"],111,112,0],[1,0,["POINT_COOKIE"],107,113,0],[1,0,["DIRECTIONAL_COOKIE"],114,115,0],[1,0,["DIRECTIONAL","_ALPHATEST_ON"],109,116,0],[1,0,["DIRECTIONAL","_ALPHABLEND_ON"],109,117,0],[1,0,["DIRECTIONAL","_ALPHAPREMULTIPLY_ON"],109,118,0],[1,0,["SPOT","_ALPHATEST_ON"],111,119,0],[1,0,["SPOT","_ALPHABLEND_ON"],111,120,0],[1,0,["SPOT","_ALPHAPREMULTIPLY_ON"],111,121,0],[1,0,["POINT_COOKIE","_ALPHATEST_ON"],107,122,0],[1,0,["POINT_COOKIE","_ALPHABLEND_ON"],107,123,0],[1,0,["POINT_COOKIE","_ALPHAPREMULTIPLY_ON"],107,124,0],[1,0,["DIRECTIONAL_COOKIE","_ALPHATEST_ON"],114,125,0],[1,0,["DIRECTIONAL_COOKIE","_ALPHABLEND_ON"],114,126,0],[1,0,["DIRECTIONAL_COOKIE","_ALPHAPREMULTIPLY_ON"],114,127,0],[1,0,["SHADOWS_DEPTH","SPOT"],111,128,0],[1,0,["DIRECTIONAL","SHADOWS_SCREEN"],129,130,0],[1,0,["DIRECTIONAL_COOKIE","SHADOWS_SCREEN"],131,132,0],[1,0,["POINT","_ALPHATEST_ON"],107,133,0],[1,0,["POINT","_ALPHABLEND_ON"],107,134,0],[1,0,["POINT","_ALPHAPREMULTIPLY_ON"],107,135,0],[1,0,["DIRECTIONAL","_SMOOTHNESS_TEXTURE_ALBEDO_CHANNEL_A"],109,136,0],[1,0,["SPOT","_SMOOTHNESS_TEXTURE_ALBEDO_CHANNEL_A"],111,137,0],[1,0,["POINT_COOKIE","_SMOOTHNESS_TEXTURE_ALBEDO_CHANNEL_A"],107,138,0],[1,0,["DIRECTIONAL_COOKIE","_SMOOTHNESS_TEXTURE_ALBEDO_CHANNEL_A"],114,139,0],[1,0,["POINT","_SMOOTHNESS_TEXTURE_ALBEDO_CHANNEL_A"],107,140,0],[1,0,["SHADOWS_DEPTH","SPOT","_ALPHATEST_ON"],111,141,0],[1,0,["SHADOWS_DEPTH","SPOT","_ALPHABLEND_ON"],111,142,0],[1,0,["SHADOWS_DEPTH","SPOT","_ALPHAPREMULTIPLY_ON"],111,143,0],[1,0,["DIRECTIONAL","SHADOWS_SCREEN","_ALPHATEST_ON"],129,144,0],[1,0,["DIRECTIONAL","SHADOWS_SCREEN","_ALPHABLEND_ON"],129,145,0],[1,0,["DIRECTIONAL","SHADOWS_SCREEN","_ALPHAPREMULTIPLY_ON"],129,146,0],[1,0,["DIRECTIONAL_COOKIE","SHADOWS_SCREEN","_ALPHATEST_ON"],131,147,0],[1,0,["DIRECTIONAL_COOKIE","SHADOWS_SCREEN","_ALPHABLEND_ON"],131,148,0],[1,0,["DIRECTIONAL_COOKIE","SHADOWS_SCREEN","_ALPHAPREMULTIPLY_ON"],131,149,0],[1,0,["SHADOWS_DEPTH","SPOT","_SMOOTHNESS_TEXTURE_ALBEDO_CHANNEL_A"],111,150,0],[1,0,["DIRECTIONAL","SHADOWS_SCREEN","_SMOOTHNESS_TEXTURE_ALBEDO_CHANNEL_A"],129,151,0],[1,0,["DIRECTIONAL_COOKIE","SHADOWS_SCREEN","_SMOOTHNESS_TEXTURE_ALBEDO_CHANNEL_A"],131,152,0]],[],0],[2,0,"ShadowCaster",8,0,[4,null],[1,null],[2,null],[[1,null],[0,null],[0,null]],[[1,null],[0,null],[0,null]],[15,null],[0,null],[0,null],[0,null],[255,null],[255,null],[[0,null],[0,null],[0,null],[8,null]],[[0,null],[0,null],[0,null],[8,null]],[[0,null],[0,null],[0,null],[8,null]],[["LIGHTMODE","SHADOWCASTER"],["SHADOWSUPPORT","true"],["RENDERTYPE","Opaque"],["PERFORMANCECHECKS","False"]],["SHADOWS_DEPTH","SHADOWS_CUBE","INSTANCING_ON","_ALPHATEST_ON","_ALPHABLEND_ON","_ALPHAPREMULTIPLY_ON","_METALLICGLOSSMAP","_PARALLAXMAP","_SMOOTHNESS_TEXTURE_ALBEDO_CHANNEL_A"],[[2,0,["SHADOWS_DEPTH"],64,65,0],[2,0,["SHADOWS_DEPTH","_ALPHATEST_ON"],153,154,0],[2,0,["SHADOWS_DEPTH","_ALPHABLEND_ON"],153,154,0],[2,0,["SHADOWS_DEPTH","_ALPHAPREMULTIPLY_ON"],153,155,0],[2,0,["SHADOWS_DEPTH","_SMOOTHNESS_TEXTURE_ALBEDO_CHANNEL_A"],64,65,0]],[],0]],[],[["_Color",0,1,1,1,1,""],["_MainTex",4,0,0,0,0,"white"],["_Cutoff",3,0.5,0,1,0,""],["_Glossiness",3,0.5,0,1,0,""],["_GlossMapScale",3,1,0,1,0,""],["_SmoothnessTextureChannel",2,0,0,0,0,""],["_Metallic",3,0,0,1,0,""],["_MetallicGlossMap",4,0,0,0,0,"white"],["_SpecularHighlights",2,1,0,0,0,""],["_GlossyReflections",2,1,0,0,0,""],["_BumpScale",2,1,0,0,0,""],["_BumpMap",4,0,0,0,0,"bump"],["_Parallax",3,0.0199999995529652,0.00499999988824129,0.0799999982118607,0,""],["_ParallaxMap",4,0,0,0,0,"black"],["_OcclusionStrength",3,1,0,1,0,""],["_OcclusionMap",4,0,0,0,0,"white"],["_EmissionColor",0,0,0,0,1,""],["_EmissionMap",4,0,0,0,0,"white"],["_DetailMask",4,0,0,0,0,"white"],["_DetailAlbedoMap",4,0,0,0,0,"grey"],["_DetailNormalMapScale",2,1,0,0,0,""],["_DetailNormalMap",4,0,0,0,0,"bump"],["_UVSec",2,0,0,0,0,""],["_Mode",2,0,0,0,0,""],["_SrcBlend",2,1,0,0,0,""],["_DstBlend",2,0,0,0,0,""],["_ZWrite",2,1,0,0,0,""]],0,"68",0,0]}],"sprites":[{"id":"984","path":"Resources/unity_builtin_extra\\InputFieldBackground","assetBundleId":"-2","data":["InputFieldBackground",1,"982",[0,0,0,0.08,0.08,0],[0.05,0.08,0,0.8125,1,0.08,-0.08,0,1,0,0.08,0.075,0,1,0.96875,-0.07,0.08,0,0.0625,1,-0.075,-0.08,0,0.03124997,0,-0.08,0.07,0,0,0.9375,-0.08,-0.05,0,0,0.1875],[6,5,4,3,4,5,1,4,3,0,1,3,2,1,0],-0.000835968181490898,-0.00160364620387554,0.999164044857025,0.998396337032318,0,0,1,1,0.3125,0.3125,0.3125,0.3125,[0,0,0,0],[-0.08,-0.08,0.08,0.08],200,32,32,32,32,16,16,0.0267509818077087,0.0513166785240173]},{"id":"980","path":"Resources/unity_builtin_extra\\Background","assetBundleId":"-2","data":["Background",1,"978",[0,0,0,0.08,0.08,0],[0.05,0.08,0,0.8125,1,0.08,-0.08,0,1,0,0.08,0.075,0,1,0.96875,-0.07,0.08,0,0.0625,1,-0.075,-0.08,0,0.03124997,0,-0.08,0.07,0,0,0.9375,-0.08,-0.05,0,0,0.1875],[6,5,4,3,4,5,1,4,3,0,1,3,2,1,0],-0.000835968181490898,-0.00160364620387554,0.999164044857025,0.998396337032318,0,0,1,1,0.3125,0.3125,0.3125,0.3125,[0,0,0,0],[-0.08,-0.08,0.08,0.08],200,32,32,32,32,16,16,0.0267509818077087,0.0513166785240173]}],"textures":[{"id":"986","type":0,"path":"Resources/unity_builtin_extra\\Knob","assetBundleId":"-2","data":["Knob",64,64,7,16,1,0,4,1,1,1],"ext":".webp"},{"id":"982","type":0,"path":"Resources/unity_builtin_extra\\InputFieldBackground","assetBundleId":"-2","data":["InputFieldBackground",32,32,6,16,1,0,4,1,1,1],"ext":".webp"},{"id":"978","type":0,"path":"Resources/unity_builtin_extra\\Background","assetBundleId":"-2","data":["Background",32,32,6,16,1,0,4,1,1,1],"ext":".webp"}],"cubemaps":[{"id":"32318","type":2,"path":"Assets/Sources/Scenes/SampleScene.unity/PrefilteredEnvironment.exr","assetBundleId":"-2","data":["","-7705196",8,0,128,0,2,1,[0,0,0.25,0.5,0,0.5,0.25,1,0.25,0,0.5,0.5,0.25,0.5,0.5,1,0.5,0,0.75,0.5,0.75,0,1,0.5,0.5,0.5,0.625,0.75,0.5,0.75,0.625,1,0.625,0.5,0.75,0.75,0.625,0.75,0.75,1,0.75,0.5,0.875,0.75,0.875,0.5,1,0.75,0.75,0.75,0.8125,0.875,0.75,0.875,0.8125,1,0.8125,0.75,0.875,0.875,0.8125,0.875,0.875,1,0.875,0.75,0.9375,0.875,0.9375,0.75,1,0.875,0.875,0.875,0.90625,0.9375,0.875,0.9375,0.90625,1,0.90625,0.875,0.9375,0.9375,0.90625,0.9375,0.9375,1,0.9375,0.875,0.96875,0.9375,0.96875,0.875,1,0.9375,0.9375,0.9375,0.953125,0.96875,0.9375,0.96875,0.953125,1,0.953125,0.9375,0.96875,0.96875,0.953125,0.96875,0.96875,1,0.96875,0.9375,0.984375,0.96875,0.984375,0.9375,1,0.96875,0.96875,0.96875,0.9765625,0.984375,0.96875,0.984375,0.9765625,1,0.9765625,0.96875,0.984375,0.984375,0.9765625,0.984375,0.984375,1,0.984375,0.96875,0.9921875,0.984375,0.9921875,0.96875,1,0.984375,0.984375,0.984375,0.98828125,0.9921875,0.984375,0.9921875,0.98828125,1,0.98828125,0.984375,0.9921875,0.9921875,0.98828125,0.9921875,0.9921875,1,0.9921875,0.984375,0.99609375,0.9921875,0.99609375,0.984375,1,0.9921875,0.9921875,0.9921875,0.994140625,0.99609375,0.9921875,0.99609375,0.994140625,1,0.994140625,0.9921875,0.99609375,0.99609375,0.994140625,0.99609375,0.99609375,1,0.99609375,0.9921875,0.998046875,0.99609375,0.998046875,0.9921875,1,0.99609375]]}],"resources":[{"id":"resources","assetBundleId":"-2","data":[[["unity_builtin_extra",0,"8"],["unity_builtin_extra",0,"30"],["unity_builtin_extra",0,"64"],["unity_builtin_extra",5,"956"],["unity_builtin_extra",1,"982"],["unity_builtin_extra",9,"984"],["unity_builtin_extra",1,"978"],["unity_builtin_extra",9,"980"],["camerablends",43,"26440"],["unity_builtin_extra",0,"288"],["unity_builtin_extra",1,"986"],["unity_builtin_extra",0,"290"],["unity_builtin_extra",0,"20"],["unity_builtin_extra",0,"116"],["ass noise profile",28,"28120"],["head noise profile",28,"28124"],["camerafovlist",22,"26380"],["unity_builtin_extra",0,"296"],["unity_builtin_extra",0,"150"],["unity_builtin_extra",5,"958"],["dotweensettings",71,"31554"],["fonts & materials/liberationsans sdf",51,"31492"],["sprite assets/emojione",73,"31480"],["style sheets/default style sheet",74,"31498"],["linebreaking leading characters",75,"31500"],["linebreaking following characters",75,"31502"],["tmp settings",72,"31482"],["billingmode",75,"32316"]],[]]}],"project-settings":[{"id":"-1","assetBundleId":"-2","data":[[["CinemachineBrain",100],["EventSystem",-1000],["TextMeshProUGUI",-100],["ToggleGroup",10],["TextContainer",-110],["CinemachinePixelPerfect",-1],["TextMeshPro",-105],["CinemachineIndependentImpulseListener",200]],[[0,"Default",0]],[[0,"Default"],[1,"TransparentFX"],[2,"Ignore Raycast"],[4,"Water"],[5,"UI"]],[0.0199999995529652,0.333333343267441,1,0.0299999993294477],[0,-9.8100004196167,0,6,2,0,1,[[0,0,0],[0,0,1],[0,0,2],[0,0,4],[0,0,5],[0,1,0],[0,1,1],[0,1,2],[0,1,4],[0,1,5],[0,2,0],[0,2,1],[0,2,2],[0,2,4],[0,2,5],[0,4,0],[0,4,1],[0,4,2],[0,4,4],[0,4,5],[0,5,0],[0,5,1],[0,5,2],[0,5,4],[0,5,5]]],[null,null,0,-9.8100004196167,3,8,1,0.200000002980232,8,0,0,0.5,0.00999999977648258,2,0.00999999977648258,1,1,1,1,0,0,[[0,0,0],[0,0,1],[0,0,2],[0,0,4],[0,0,5],[0,1,0],[0,1,1],[0,1,2],[0,1,4],[0,1,5],[0,2,0],[0,2,1],[0,2,2],[0,2,4],[0,2,5],[0,4,0],[0,4,1],[0,4,2],[0,4,4],[0,4,5],[0,5,0],[0,5,1],[0,5,2],[0,5,4],[0,5,5]]],[[[[],["Very Low","Low","Medium","High","Very High","Ultra"],0,0,0,0.300000011920929,1,15,0,1,0,0,0,0,0,1,2,4,0,0,0.333333343267441,0.0666666701436043,0.200000002980232,0.466666668653488,0,0,16,2,0,3,512,0,1,2,512,1,1024,0],[[],["Very Low","Low","Medium","High","Very High","Ultra"],0,0,0,0.400000005960464,1,20,0,1,0,0,0,0,0,0,2,16,0,0,0.333333343267441,0.0666666701436043,0.200000002980232,0.466666668653488,0,0,16,2,0,3,512,0,1,2,512,1,1024,1],[[],["Very Low","Low","Medium","High","Very High","Ultra"],1,1,0,0.699999988079071,1,20,0,1,0,0,0,0,0,0,2,64,1,0,0.333333343267441,0.0666666701436043,0.200000002980232,0.466666668653488,0,1,16,2,0,3,512,0,1,2,512,1,1024,2],[[],["Very Low","Low","Medium","High","Very High","Ultra"],2,1,0,1,2,40,1,1,1,0,1,0,0,0,2,256,2,1,0.333333343267441,0.0666666701436043,0.200000002980232,0.466666668653488,0,1,16,2,1,3,512,0,1,2,512,1,1024,3],[[],["Very Low","Low","Medium","High","Very High","Ultra"],2,2,2,1.5,2,70,1,1,2,1,1,0,0,0,2,1024,3,1,0.333333343267441,0.0666666701436043,0.200000002980232,0.466666668653488,0,1,16,2,1,3,512,0,1,2,512,1,1024,4],[[],["Very Low","Low","Medium","High","Very High","Ultra"],2,2,2,2,4,150,1,1,2,1,1,0,0,0,2,4096,4,1,0.333333343267441,0.0666666701436043,0.200000002980232,0.466666668653488,0,1,16,2,1,3,512,0,1,2,512,1,1024,5]],["Very Low","Low","Medium","High","Very High","Ultra"],2,2,2,2,4,150,1,1,2,1,1,0,0,0,2,4096,4,1,0.333333343267441,0.0666666701436043,0.200000002980232,0.466666668653488,0,1,16,2,1,3,512,0,1,2,512,1,1024,5],0,1,0,2,0]}]}